garden_ai/__init__.py
garden_ai/__main__.py
garden_ai/_version.py
garden_ai/app/__init__.py
garden_ai/app/console.py
garden_ai/app/main.py
garden_ai/app/mcp.py
garden_ai/backend_client.py
garden_ai/client.py
garden_ai/constants.py
garden_ai/garden_file_adapter.py
garden_ai/gardens.py
garden_ai/hpc/__init__.py
garden_ai/hpc/executor.py
garden_ai/hpc/functions.py
garden_ai/hpc/gardens/mlip_garden.py
garden_ai/hpc/groundhog.py
garden_ai/hpc/utils.py
garden_ai/mcp/README.md
garden_ai/mcp/__init__.py
garden_ai/mcp/config_add.py
garden_ai/mcp/mlip.py
garden_ai/mcp/server.py
garden_ai/modal/__init__.py
garden_ai/modal/classes.py
garden_ai/modal/functions.py
garden_ai/schemas/__init__.py
garden_ai/schemas/datacite.py
garden_ai/schemas/entrypoint.py
garden_ai/schemas/garden.py
garden_ai/schemas/hpc.py
garden_ai/schemas/modal.py
garden_ai/schemas/schema_utils.py
garden_ai/utils/__init__.py
garden_ai/utils/interactive_cli.py
garden_ai-3.2.1.dist-info/WHEEL
garden_ai-3.2.1.dist-info/entry_points.txt
garden_ai-3.2.1.dist-info/METADATA
garden_ai-3.2.1.dist-info/RECORD
