Metadata-Version: 2.3
Name: garden-ai
Version: 3.2.1
Summary: Garden: tools to simplify access to scientific AI advances.
Author: Garden Team
Author-email: Garden Team <labs@globus.org>
License: MIT
Requires-Dist: cryptography>=44.0.0,<45.0.0
Requires-Dist: requests>=2.20.0
Requires-Dist: gitpython>=3.1.35,<4.0.0
Requires-Dist: globus-sdk>=3.34.0,<4.0.0
Requires-Dist: pydantic>=2.7.2,<3.0.0
Requires-Dist: typer>=0.12.3
Requires-Dist: click>=8.0.0,<8.2.0
Requires-Dist: jinja2>=3.1.2,<4.0.0
Requires-Dist: huggingface-hub==0.18.0
Requires-Dist: pyyaml>=6.0,<7.0
Requires-Dist: globus-compute-sdk>=4.0.0
Requires-Dist: tabulate>=0.9.0,<1.0.0
Requires-Dist: types-tabulate>=0.9.0.3,<1.0.0.0
Requires-Dist: nbformat>=5.9.2,<6.0.0
Requires-Dist: ipython<8.13
Requires-Dist: ipywidgets>=8.1.3,<9.0
Requires-Dist: boto3>=1.29,<2.0
Requires-Dist: boto3-stubs>=1.29,<2.0
Requires-Dist: urllib3<2 ; python_full_version < '3.10'
Requires-Dist: urllib3>=2.2.1 ; python_full_version >= '3.10'
Requires-Dist: python-dotenv>=1.0.1,<2.0
Requires-Dist: pydantic-core>=2.18.4,<3.0.0
Requires-Dist: modal>=1.0.0,<2.0.0
Requires-Dist: mixpanel>=4.10.1,<5.0.0
Requires-Dist: marshmallow<4.0.0
Requires-Dist: h2>=4.3.0
Requires-Dist: groundhog-hpc>=0.5.0
Requires-Dist: mcp>=1.0.0 ; extra == 'mcp'
Requires-Dist: uv>=0.8.0 ; extra == 'mcp'
Requires-Dist: ase ; extra == 'mlip'
Maintainer: Globus Labs, Owen Price Skelly, Will Engler, Hayden Holbrook, Ben Blaiszik
Maintainer-email: Globus Labs <labs@globus.org>
Requires-Python: >=3.10
Project-URL: documentation, https://garden-ai.readthedocs.io/en/latest/
Project-URL: homepage, https://thegardens.ai
Project-URL: repository, https://github.com/Garden-AI/garden
Provides-Extra: mcp
Provides-Extra: mlip
